{
	"type": "TypeAPL",
	"prepullActions": [
		{ "action": { "castSpell": { "spellId": { "spellId": 13165 } } }, "doAtValue": { "const": { "val": "-10s" } } },
		{ "action": { "castSpell": { "spellId": { "spellId": 1130 } } }, "doAtValue": { "const": { "val": "-7s" } } },
		{ "action": { "castSpell": { "spellId": { "spellId": 13812 } } }, "doAtValue": { "const": { "val": "-5s" } } },
		{ "action": { "castSpell": { "spellId": { "otherId": "OtherActionPotion" } } }, "doAtValue": { "const": { "val": "-2.3s" } } },
		{ "action": { "castSpell": { "spellId": { "spellId": 19434 } } }, "doAtValue": { "const": { "val": "-2.3s" } } }
	],
	"priorityList": [
		{
			"action": { "condition": { "not": { "val": { "sequenceIsComplete": { "sequenceName": "opener" } } } }, "groupReference": { "groupName": "Opener" } }
		},
		{ "action": { "groupReference": { "groupName": "Cooldowns" } } },
		{
			"action": {
				"condition": { "not": { "val": { "dotIsActive": { "spellId": { "spellId": 1978 } } } } },
				"castSpell": { "spellId": { "spellId": 1978 } }
			}
		},
		{ "action": { "castSpell": { "spellId": { "spellId": 53209 } } } },
		{
			"action": {
				"condition": { "auraIsActive": { "auraId": { "spellId": 120668, "tag": -1 }, "includeReactionTime": true } },
				"castSpell": { "spellId": { "spellId": 120360 } }
			}
		},
		{ "action": { "castSpell": { "spellId": { "spellId": 131894 } } } },
		{ "action": { "castSpell": { "spellId": { "spellId": 82928 } } } },
		{ "action": { "condition": { "isExecutePhase": { "threshold": "E20" } }, "castSpell": { "spellId": { "spellId": 53351 } } } },
		{ "action": { "castSpell": { "spellId": { "spellId": 120697 } } } },
		{ "action": { "condition": { "variableRef": { "name": "Steady Focus" } }, "castSpell": { "spellId": { "spellId": 56641 } } } },
		{ "action": { "castSpell": { "spellId": { "spellId": 120360 } } } },
		{ "action": { "castSpell": { "spellId": { "spellId": 117050 } } } },
		{ "action": { "castSpell": { "spellId": { "spellId": 109259 } } } },
		{ "action": { "condition": { "variableRef": { "name": "Aimed" } }, "castSpell": { "spellId": { "spellId": 19434 } } } },
		{ "action": { "castSpell": { "spellId": { "spellId": 56641 } } } }
	],
	"groups": [
		{
			"name": "Opener",
			"actions": [
				{
					"action": {
						"sequence": {
							"name": "step 1",
							"actions": [
								{ "castSpell": { "spellId": { "spellId": 1978 } } },
								{
									"wait": {
										"duration": { "math": { "op": "OpSub", "lhs": { "gcdTimeToReady": {} }, "rhs": { "const": { "val": "100ms" } } } }
									}
								},
								{ "castSpell": { "spellId": { "spellId": 82726 } } },
								{
									"wait": {
										"duration": {
											"max": {
												"vals": [
													{ "focusTimeToTarget": { "targetFocus": { "spellCurrentCost": { "spellId": { "spellId": 131894 } } } } },
													{ "gcdTimeToReady": {} }
												]
											}
										}
									}
								}
							]
						}
					}
				},
				{
					"action": {
						"sequence": {
							"name": "step 2",
							"actions": [{ "castSpell": { "spellId": { "spellId": 131894 } } }, { "wait": { "duration": { "gcdTimeToReady": {} } } }]
						}
					}
				},
				{ "action": { "groupReference": { "groupName": "Cooldowns" } } },
				{
					"action": {
						"sequence": {
							"name": "step 3",
							"actions": [
								{ "castSpell": { "spellId": { "spellId": 53209 } } },
								{ "castSpell": { "spellId": { "spellId": 56641 } } },
								{ "castSpell": { "spellId": { "spellId": 56641 } } }
							]
						}
					}
				},
				{ "action": { "sequence": { "name": "opener", "actions": [{ "castSpell": { "spellId": { "spellId": 117050 } } }] } } },
				{ "action": { "sequence": { "name": "opener", "actions": [{ "castSpell": { "spellId": { "spellId": 109259 } } }] } } },
				{
					"action": {
						"condition": { "auraIsActive": { "auraId": { "spellId": 120668, "tag": -1 }, "includeReactionTime": true } },
						"sequence": { "name": "opener", "actions": [{ "castSpell": { "spellId": { "spellId": 120360 } } }] }
					}
				}
			]
		},
		{
			"name": "Cooldowns",
			"actions": [
				{ "action": { "castSpell": { "spellId": { "spellId": 126734 } } } },
				{ "action": { "castSpell": { "spellId": { "spellId": 53401 } } } },
				{
					"action": {
						"condition": { "cmp": { "op": "OpLe", "lhs": { "currentFocus": {} }, "rhs": { "const": { "val": "50" } } } },
						"castSpell": { "spellId": { "spellId": 82726 } }
					}
				},
				{ "action": { "castSpell": { "spellId": { "spellId": 3045 } } } },
				{ "action": { "castSpell": { "spellId": { "spellId": 33697 } } } },
				{ "action": { "castSpell": { "spellId": { "spellId": 26297 } } } },
				{ "action": { "autocastOtherCooldowns": {} } },
				{ "action": { "castSpell": { "spellId": { "spellId": 114206, "tag": -1 } } } },
				{ "action": { "castSpell": { "spellId": { "spellId": 2825, "tag": -1 } } } },
				{ "action": { "castSpell": { "spellId": { "spellId": 120668, "tag": -1 } } } },
				{ "action": { "groupReference": { "groupName": "Second Pot" } } },
				{ "action": { "castSpell": { "spellId": { "spellId": 121818 } } } },
				{ "action": { "castSpell": { "spellId": { "spellId": 120679 } } } }
			]
		},
		{
			"name": "Second Pot",
			"actions": [
				{
					"action": {
						"condition": {
							"or": { "vals": [{ "isExecutePhase": { "threshold": "E20" } }, { "dotIsActive": { "spellId": { "spellId": 131894 } } }] }
						},
						"castSpell": { "spellId": { "itemId": 76089 } }
					}
				}
			]
		}
	],
	"valueVariables": [
		{
			"name": "Steady Focus",
			"value": {
				"and": {
					"vals": [
						{
							"cmp": {
								"op": "OpEq",
								"lhs": { "auraNumStacks": { "auraId": { "spellId": 53224, "tag": 2 } } },
								"rhs": { "const": { "val": "2" } }
							}
						},
						{
							"cmp": {
								"op": "OpLe",
								"lhs": { "auraRemainingTime": { "auraId": { "spellId": 53224, "tag": 1 } } },
								"rhs": { "const": { "val": "7s" } }
							}
						}
					]
				}
			}
		},
		{
			"name": "Aimed",
			"value": {
				"or": {
					"vals": [
						{ "and": { "vals": [{ "cmp": { "op": "OpGe", "lhs": { "currentFocus": {} }, "rhs": { "const": { "val": "85" } } } }] } },
						{ "and": { "vals": [{ "auraIsActive": { "auraId": { "spellId": 3045 }, "includeReactionTime": true } }] } },
						{
							"and": {
								"vals": [
									{
										"not": {
											"val": {
												"cmp": {
													"op": "OpLe",
													"lhs": { "spellTimeToReady": { "spellId": { "spellId": 53209 } } },
													"rhs": { "const": { "val": "3s" } }
												}
											}
										}
									},
									{
										"not": {
											"val": {
												"cmp": {
													"op": "OpLe",
													"lhs": { "spellTimeToReady": { "spellId": { "spellId": 131894 } } },
													"rhs": { "const": { "val": "3s" } }
												}
											}
										}
									},
									{ "not": { "val": { "spellIsReady": { "spellId": { "spellId": 131894 } } } } }
								]
							}
						}
					]
				}
			}
		}
	]
}
